viewerdevs/__init__.py
viewerdevs-1.0.0.dist-info/METADATA
viewerdevs-1.0.0.dist-info/WHEEL
viewerdevs-1.0.0.dist-info/top_level.txt
viewerdevs-1.0.0.dist-info/RECORD
