Metadata-Version: 2.1
Name: viewerdevs
Version: 1.0.0
Summary: Doujin/Image Viewer for nhentaidevs.
Home-page: https://pypi.org/project/viewerdevs
Author: John Lester Dev :>
Author-email: johnlesterincbusiness@gmail.com
License: UNKNOWN
Keywords: nhentaidevs,tkinter,window
Platform: UNKNOWN
Classifier: Programming Language :: Python :: 3
Classifier: Operating System :: OS Independent
Requires-Python: >=3.8
Requires-Dist: nhentaidevs
Requires-Dist: pillow
Requires-Dist: click
Requires-Dist: tqdm
